test_in_august/__init__.py
test_in_august/py.typed
test_in_august/tests/__init__.py
test_in_august/tests/resources/.gitignore
test_in_august/tests/resources/__init__.py
test_in_august/tests/test_base_exception.py
test_in_august-0.0.0.dist-info/LICENSE
test_in_august-0.0.0.dist-info/METADATA
test_in_august-0.0.0.dist-info/WHEEL
test_in_august-0.0.0.dist-info/RECORD
